{
  "id": "09e26789-cee9-4481-8616-440a1b60246c",
  "width": 15,
  "height": 15,
  "cells": [
    [
      {
        "id": "0-0",
        "row": 0,
        "col": 0,
        "isBlack": false,
        "correctChar": "C",
        "userChar": "",
        "number": 1
      },
      {
        "id": "0-1",
        "row": 0,
        "col": 1,
        "isBlack": false,
        "correctChar": "H",
        "userChar": "",
        "number": 2
      },
      {
        "id": "0-2",
        "row": 0,
        "col": 2,
        "isBlack": false,
        "correctChar": "E",
        "userChar": "",
        "number": 3
      },
      {
        "id": "0-3",
        "row": 0,
        "col": 3,
        "isBlack": true,
        "correctChar": null,
        "userChar": ""
      },
      {
        "id": "0-4",
        "row": 0,
        "col": 4,
        "isBlack": false,
        "correctChar": "E",
        "userChar": "",
        "number": 4
      },
      {
        "id": "0-5",
        "row": 0,
        "col": 5,
        "isBlack": false,
        "correctChar": "D",
        "userChar": "",
        "number": 5
      },
      {
        "id": "0-6",
        "row": 0,
        "col": 6,
        "isBlack": false,
        "correctChar": "E",
        "userChar": "",
        "number": 6
      },
      {
        "id": "0-7",
        "row": 0,
        "col": 7,
        "isBlack": false,
        "correctChar": "R",
        "userChar": "",
        "number": 7
      },
      {
        "id": "0-8",
        "row": 0,
        "col": 8,
        "isBlack": false,
        "correctChar": "A",
        "userChar": "",
        "number": 8
      },
      {
        "id": "0-9",
        "row": 0,
        "col": 9,
        "isBlack": true,
        "correctChar": null,
        "userChar": ""
      },
      {
        "id": "0-10",
        "row": 0,
        "col": 10,
        "isBlack": false,
        "correctChar": "T",
        "userChar": "",
        "number": 9
      },
      {
        "id": "0-11",
        "row": 0,
        "col": 11,
        "isBlack": false,
        "correctChar": "U",
        "userChar": "",
        "number": 10
      },
      {
        "id": "0-12",
        "row": 0,
        "col": 12,
        "isBlack": false,
        "correctChar": "A",
        "userChar": "",
        "number": 11
      },
      {
        "id": "0-13",
        "row": 0,
        "col": 13,
        "isBlack": true,
        "correctChar": null,
        "userChar": ""
      },
      {
        "id": "0-14",
        "row": 0,
        "col": 14,
        "isBlack": true,
        "correctChar": null,
        "userChar": ""
      }
    ],
    [
      {
        "id": "1-0",
        "row": 1,
        "col": 0,
        "isBlack": false,
        "correctChar": "O",
        "userChar": "",
        "number": 12
      },
      {
        "id": "1-1",
        "row": 1,
        "col": 1,
        "isBlack": false,
        "correctChar": "O",
        "userChar": ""
      },
      {
        "id": "1-2",
        "row": 1,
        "col": 2,
        "isBlack": false,
        "correctChar": "S",
        "userChar": ""
      },
      {
        "id": "1-3",
        "row": 1,
        "col": 3,
        "isBlack": true,
        "correctChar": null,
        "userChar": ""
      },
      {
        "id": "1-4",
        "row": 1,
        "col": 4,
        "isBlack": false,
        "correctChar": "V",
        "userChar": "",
        "number": 13
      },
      {
        "id": "1-5",
        "row": 1,
        "col": 5,
        "isBlack": false,
        "correctChar": "E",
        "userChar": ""
      },
      {
        "id": "1-6",
        "row": 1,
        "col": 6,
        "isBlack": false,
        "correctChar": "L",
        "userChar": ""
      },
      {
        "id": "1-7",
        "row": 1,
        "col": 7,
        "isBlack": false,
        "correctChar": "O",
        "userChar": ""
      },
      {
        "id": "1-8",
        "row": 1,
        "col": 8,
        "isBlack": false,
        "correctChar": "C",
        "userChar": ""
      },
      {
        "id": "1-9",
        "row": 1,
        "col": 9,
        "isBlack": false,
        "correctChar": "E",
        "userChar": "",
        "number": 14
      },
      {
        "id": "1-10",
        "row": 1,
        "col": 10,
        "isBlack": false,
        "correctChar": "M",
        "userChar": ""
      },
      {
        "id": "1-11",
        "row": 1,
        "col": 11,
        "isBlack": false,
        "correctChar": "E",
        "userChar": ""
      },
      {
        "id": "1-12",
        "row": 1,
        "col": 12,
        "isBlack": false,
        "correctChar": "N",
        "userChar": ""
      },
      {
        "id": "1-13",
        "row": 1,
        "col": 13,
        "isBlack": false,
        "correctChar": "T",
        "userChar": "",
        "number": 15
      },
      {
        "id": "1-14",
        "row": 1,
        "col": 14,
        "isBlack": false,
        "correctChar": "E",
        "userChar": "",
        "number": 16
      }
    ],
    [
      {
        "id": "2-0",
        "row": 2,
        "col": 0,
        "isBlack": false,
        "correctChar": "S",
        "userChar": "",
        "number": 17
      },
      {
        "id": "2-1",
        "row": 2,
        "col": 1,
        "isBlack": false,
        "correctChar": "T",
        "userChar": ""
      },
      {
        "id": "2-2",
        "row": 2,
        "col": 2,
        "isBlack": false,
        "correctChar": "A",
        "userChar": ""
      },
      {
        "id": "2-3",
        "row": 2,
        "col": 3,
        "isBlack": true,
        "correctChar": null,
        "userChar": ""
      },
      {
        "id": "2-4",
        "row": 2,
        "col": 4,
        "isBlack": false,
        "correctChar": "E",
        "userChar": "",
        "number": 18
      },
      {
        "id": "2-5",
        "row": 2,
        "col": 5,
        "isBlack": false,
        "correctChar": "V",
        "userChar": ""
      },
      {
        "id": "2-6",
        "row": 2,
        "col": 6,
        "isBlack": false,
        "correctChar": "I",
        "userChar": ""
      },
      {
        "id": "2-7",
        "row": 2,
        "col": 7,
        "isBlack": false,
        "correctChar": "D",
        "userChar": ""
      },
      {
        "id": "2-8",
        "row": 2,
        "col": 8,
        "isBlack": false,
        "correctChar": "E",
        "userChar": ""
      },
      {
        "id": "2-9",
        "row": 2,
        "col": 9,
        "isBlack": false,
        "correctChar": "N",
        "userChar": ""
      },
      {
        "id": "2-10",
        "row": 2,
        "col": 10,
        "isBlack": false,
        "correctChar": "Z",
        "userChar": ""
      },
      {
        "id": "2-11",
        "row": 2,
        "col": 11,
        "isBlack": false,
        "correctChar": "I",
        "userChar": ""
      },
      {
        "id": "2-12",
        "row": 2,
        "col": 12,
        "isBlack": false,
        "correctChar": "A",
        "userChar": ""
      },
      {
        "id": "2-13",
        "row": 2,
        "col": 13,
        "isBlack": false,
        "correctChar": "R",
        "userChar": ""
      },
      {
        "id": "2-14",
        "row": 2,
        "col": 14,
        "isBlack": false,
        "correctChar": "E",
        "userChar": ""
      }
    ],
    [
      {
        "id": "3-0",
        "row": 3,
        "col": 0,
        "isBlack": false,
        "correctChar": "I",
        "userChar": "",
        "number": 19
      },
      {
        "id": "3-1",
        "row": 3,
        "col": 1,
        "isBlack": false,
        "correctChar": "E",
        "userChar": ""
      },
      {
        "id": "3-2",
        "row": 3,
        "col": 2,
        "isBlack": false,
        "correctChar": "M",
        "userChar": ""
      },
      {
        "id": "3-3",
        "row": 3,
        "col": 3,
        "isBlack": false,
        "correctChar": "A",
        "userChar": "",
        "number": 20
      },
      {
        "id": "3-4",
        "row": 3,
        "col": 4,
        "isBlack": false,
        "correctChar": "L",
        "userChar": ""
      },
      {
        "id": "3-5",
        "row": 3,
        "col": 5,
        "isBlack": false,
        "correctChar": "E",
        "userChar": ""
      },
      {
        "id": "3-6",
        "row": 3,
        "col": 6,
        "isBlack": true,
        "correctChar": null,
        "userChar": ""
      },
      {
        "id": "3-7",
        "row": 3,
        "col": 7,
        "isBlack": false,
        "correctChar": "E",
        "userChar": "",
        "number": 21
      },
      {
        "id": "3-8",
        "row": 3,
        "col": 8,
        "isBlack": false,
        "correctChar": "T",
        "userChar": ""
      },
      {
        "id": "3-9",
        "row": 3,
        "col": 9,
        "isBlack": false,
        "correctChar": "E",
        "userChar": ""
      },
      {
        "id": "3-10",
        "row": 3,
        "col": 10,
        "isBlack": true,
        "correctChar": null,
        "userChar": ""
      },
      {
        "id": "3-11",
        "row": 3,
        "col": 11,
        "isBlack": true,
        "correctChar": null,
        "userChar": ""
      },
      {
        "id": "3-12",
        "row": 3,
        "col": 12,
        "isBlack": false,
        "correctChar": "G",
        "userChar": "",
        "number": 22
      },
      {
        "id": "3-13",
        "row": 3,
        "col": 13,
        "isBlack": false,
        "correctChar": "E",
        "userChar": ""
      },
      {
        "id": "3-14",
        "row": 3,
        "col": 14,
        "isBlack": false,
        "correctChar": "B",
        "userChar": ""
      }
    ],
    [
      {
        "id": "4-0",
        "row": 4,
        "col": 0,
        "isBlack": true,
        "correctChar": null,
        "userChar": ""
      },
      {
        "id": "4-1",
        "row": 4,
        "col": 1,
        "isBlack": false,
        "correctChar": "L",
        "userChar": "",
        "number": 23
      },
      {
        "id": "4-2",
        "row": 4,
        "col": 2,
        "isBlack": false,
        "correctChar": "I",
        "userChar": ""
      },
      {
        "id": "4-3",
        "row": 4,
        "col": 3,
        "isBlack": false,
        "correctChar": "L",
        "userChar": ""
      },
      {
        "id": "4-4",
        "row": 4,
        "col": 4,
        "isBlack": false,
        "correctChar": "Y",
        "userChar": ""
      },
      {
        "id": "4-5",
        "row": 4,
        "col": 5,
        "isBlack": true,
        "correctChar": null,
        "userChar": ""
      },
      {
        "id": "4-6",
        "row": 4,
        "col": 6,
        "isBlack": true,
        "correctChar": null,
        "userChar": ""
      },
      {
        "id": "4-7",
        "row": 4,
        "col": 7,
        "isBlack": true,
        "correctChar": null,
        "userChar": ""
      },
      {
        "id": "4-8",
        "row": 4,
        "col": 8,
        "isBlack": false,
        "correctChar": "O",
        "userChar": "",
        "number": 24
      },
      {
        "id": "4-9",
        "row": 4,
        "col": 9,
        "isBlack": false,
        "correctChar": "G",
        "userChar": ""
      },
      {
        "id": "4-10",
        "row": 4,
        "col": 10,
        "isBlack": false,
        "correctChar": "N",
        "userChar": "",
        "number": 25
      },
      {
        "id": "4-11",
        "row": 4,
        "col": 11,
        "isBlack": false,
        "correctChar": "O",
        "userChar": "",
        "number": 26
      },
      {
        "id": "4-12",
        "row": 4,
        "col": 12,
        "isBlack": false,
        "correctChar": "R",
        "userChar": ""
      },
      {
        "id": "4-13",
        "row": 4,
        "col": 13,
        "isBlack": false,
        "correctChar": "A",
        "userChar": ""
      },
      {
        "id": "4-14",
        "row": 4,
        "col": 14,
        "isBlack": true,
        "correctChar": null,
        "userChar": ""
      }
    ],
    [
      {
        "id": "5-0",
        "row": 5,
        "col": 0,
        "isBlack": true,
        "correctChar": null,
        "userChar": ""
      },
      {
        "id": "5-1",
        "row": 5,
        "col": 1,
        "isBlack": true,
        "correctChar": null,
        "userChar": ""
      },
      {
        "id": "5-2",
        "row": 5,
        "col": 2,
        "isBlack": true,
        "correctChar": null,
        "userChar": ""
      },
      {
        "id": "5-3",
        "row": 5,
        "col": 3,
        "isBlack": false,
        "correctChar": "L",
        "userChar": "",
        "number": 27
      },
      {
        "id": "5-4",
        "row": 5,
        "col": 4,
        "isBlack": false,
        "correctChar": "N",
        "userChar": ""
      },
      {
        "id": "5-5",
        "row": 5,
        "col": 5,
        "isBlack": false,
        "correctChar": "N",
        "userChar": "",
        "number": 28
      },
      {
        "id": "5-6",
        "row": 5,
        "col": 6,
        "isBlack": true,
        "correctChar": null,
        "userChar": ""
      },
      {
        "id": "5-7",
        "row": 5,
        "col": 7,
        "isBlack": true,
        "correctChar": null,
        "userChar": ""
      },
      {
        "id": "5-8",
        "row": 5,
        "col": 8,
        "isBlack": true,
        "correctChar": null,
        "userChar": ""
      },
      {
        "id": "5-9",
        "row": 5,
        "col": 9,
        "isBlack": false,
        "correctChar": "O",
        "userChar": "",
        "number": 29
      },
      {
        "id": "5-10",
        "row": 5,
        "col": 10,
        "isBlack": false,
        "correctChar": "C",
        "userChar": ""
      },
      {
        "id": "5-11",
        "row": 5,
        "col": 11,
        "isBlack": false,
        "correctChar": "C",
        "userChar": ""
      },
      {
        "id": "5-12",
        "row": 5,
        "col": 12,
        "isBlack": false,
        "correctChar": "A",
        "userChar": ""
      },
      {
        "id": "5-13",
        "row": 5,
        "col": 13,
        "isBlack": false,
        "correctChar": "S",
        "userChar": ""
      },
      {
        "id": "5-14",
        "row": 5,
        "col": 14,
        "isBlack": false,
        "correctChar": "O",
        "userChar": "",
        "number": 30
      }
    ],
    [
      {
        "id": "6-0",
        "row": 6,
        "col": 0,
        "isBlack": false,
        "correctChar": "A",
        "userChar": "",
        "number": 31
      },
      {
        "id": "6-1",
        "row": 6,
        "col": 1,
        "isBlack": false,
        "correctChar": "S",
        "userChar": "",
        "number": 32
      },
      {
        "id": "6-2",
        "row": 6,
        "col": 2,
        "isBlack": false,
        "correctChar": "O",
        "userChar": "",
        "number": 33
      },
      {
        "id": "6-3",
        "row": 6,
        "col": 3,
        "isBlack": true,
        "correctChar": null,
        "userChar": ""
      },
      {
        "id": "6-4",
        "row": 6,
        "col": 4,
        "isBlack": true,
        "correctChar": null,
        "userChar": ""
      },
      {
        "id": "6-5",
        "row": 6,
        "col": 5,
        "isBlack": false,
        "correctChar": "O",
        "userChar": "",
        "number": 34
      },
      {
        "id": "6-6",
        "row": 6,
        "col": 6,
        "isBlack": false,
        "correctChar": "G",
        "userChar": "",
        "number": 35
      },
      {
        "id": "6-7",
        "row": 6,
        "col": 7,
        "isBlack": false,
        "correctChar": "G",
        "userChar": "",
        "number": 36
      },
      {
        "id": "6-8",
        "row": 6,
        "col": 8,
        "isBlack": false,
        "correctChar": "I",
        "userChar": "",
        "number": 37
      },
      {
        "id": "6-9",
        "row": 6,
        "col": 9,
        "isBlack": true,
        "correctChar": null,
        "userChar": ""
      },
      {
        "id": "6-10",
        "row": 6,
        "col": 10,
        "isBlack": false,
        "correctChar": "D",
        "userChar": "",
        "number": 38
      },
      {
        "id": "6-11",
        "row": 6,
        "col": 11,
        "isBlack": false,
        "correctChar": "O",
        "userChar": ""
      },
      {
        "id": "6-12",
        "row": 6,
        "col": 12,
        "isBlack": false,
        "correctChar": "M",
        "userChar": ""
      },
      {
        "id": "6-13",
        "row": 6,
        "col": 13,
        "isBlack": false,
        "correctChar": "U",
        "userChar": ""
      },
      {
        "id": "6-14",
        "row": 6,
        "col": 14,
        "isBlack": false,
        "correctChar": "S",
        "userChar": ""
      }
    ],
    [
      {
        "id": "7-0",
        "row": 7,
        "col": 0,
        "isBlack": false,
        "correctChar": "B",
        "userChar": "",
        "number": 39
      },
      {
        "id": "7-1",
        "row": 7,
        "col": 1,
        "isBlack": false,
        "correctChar": "A",
        "userChar": ""
      },
      {
        "id": "7-2",
        "row": 7,
        "col": 2,
        "isBlack": false,
        "correctChar": "B",
        "userChar": ""
      },
      {
        "id": "7-3",
        "row": 7,
        "col": 3,
        "isBlack": true,
        "correctChar": null,
        "userChar": ""
      },
      {
        "id": "7-4",
        "row": 7,
        "col": 4,
        "isBlack": true,
        "correctChar": null,
        "userChar": ""
      },
      {
        "id": "7-5",
        "row": 7,
        "col": 5,
        "isBlack": false,
        "correctChar": "I",
        "userChar": "",
        "number": 40
      },
      {
        "id": "7-6",
        "row": 7,
        "col": 6,
        "isBlack": false,
        "correctChar": "L",
        "userChar": ""
      },
      {
        "id": "7-7",
        "row": 7,
        "col": 7,
        "isBlack": false,
        "correctChar": "A",
        "userChar": ""
      },
      {
        "id": "7-8",
        "row": 7,
        "col": 8,
        "isBlack": false,
        "correctChar": "N",
        "userChar": ""
      },
      {
        "id": "7-9",
        "row": 7,
        "col": 9,
        "isBlack": false,
        "correctChar": "R",
        "userChar": "",
        "number": 41
      },
      {
        "id": "7-10",
        "row": 7,
        "col": 10,
        "isBlack": true,
        "correctChar": null,
        "userChar": ""
      },
      {
        "id": "7-11",
        "row": 7,
        "col": 11,
        "isBlack": true,
        "correctChar": null,
        "userChar": ""
      },
      {
        "id": "7-12",
        "row": 7,
        "col": 12,
        "isBlack": false,
        "correctChar": "M",
        "userChar": "",
        "number": 42
      },
      {
        "id": "7-13",
        "row": 7,
        "col": 13,
        "isBlack": false,
        "correctChar": "R",
        "userChar": ""
      },
      {
        "id": "7-14",
        "row": 7,
        "col": 14,
        "isBlack": false,
        "correctChar": "S",
        "userChar": ""
      }
    ],
    [
      {
        "id": "8-0",
        "row": 8,
        "col": 0,
        "isBlack": false,
        "correctChar": "I",
        "userChar": "",
        "number": 43
      },
      {
        "id": "8-1",
        "row": 8,
        "col": 1,
        "isBlack": false,
        "correctChar": "N",
        "userChar": ""
      },
      {
        "id": "8-2",
        "row": 8,
        "col": 2,
        "isBlack": false,
        "correctChar": "A",
        "userChar": ""
      },
      {
        "id": "8-3",
        "row": 8,
        "col": 3,
        "isBlack": false,
        "correctChar": "M",
        "userChar": "",
        "number": 44
      },
      {
        "id": "8-4",
        "row": 8,
        "col": 4,
        "isBlack": false,
        "correctChar": "A",
        "userChar": "",
        "number": 45
      },
      {
        "id": "8-5",
        "row": 8,
        "col": 5,
        "isBlack": true,
        "correctChar": null,
        "userChar": ""
      },
      {
        "id": "8-6",
        "row": 8,
        "col": 6,
        "isBlack": false,
        "correctChar": "I",
        "userChar": "",
        "number": 46
      },
      {
        "id": "8-7",
        "row": 8,
        "col": 7,
        "isBlack": false,
        "correctChar": "S",
        "userChar": ""
      },
      {
        "id": "8-8",
        "row": 8,
        "col": 8,
        "isBlack": false,
        "correctChar": "C",
        "userChar": ""
      },
      {
        "id": "8-9",
        "row": 8,
        "col": 9,
        "isBlack": false,
        "correctChar": "O",
        "userChar": ""
      },
      {
        "id": "8-10",
        "row": 8,
        "col": 10,
        "isBlack": true,
        "correctChar": null,
        "userChar": ""
      },
      {
        "id": "8-11",
        "row": 8,
        "col": 11,
        "isBlack": true,
        "correctChar": null,
        "userChar": ""
      },
      {
        "id": "8-12",
        "row": 8,
        "col": 12,
        "isBlack": false,
        "correctChar": "I",
        "userChar": "",
        "number": 47
      },
      {
        "id": "8-13",
        "row": 8,
        "col": 13,
        "isBlack": false,
        "correctChar": "E",
        "userChar": ""
      },
      {
        "id": "8-14",
        "row": 8,
        "col": 14,
        "isBlack": false,
        "correctChar": "O",
        "userChar": ""
      }
    ],
    [
      {
        "id": "9-0",
        "row": 9,
        "col": 0,
        "isBlack": false,
        "correctChar": "E",
        "userChar": "",
        "number": 48
      },
      {
        "id": "9-1",
        "row": 9,
        "col": 1,
        "isBlack": false,
        "correctChar": "D",
        "userChar": ""
      },
      {
        "id": "9-2",
        "row": 9,
        "col": 2,
        "isBlack": false,
        "correctChar": "M",
        "userChar": ""
      },
      {
        "id": "9-3",
        "row": 9,
        "col": 3,
        "isBlack": false,
        "correctChar": "O",
        "userChar": ""
      },
      {
        "id": "9-4",
        "row": 9,
        "col": 4,
        "isBlack": false,
        "correctChar": "N",
        "userChar": ""
      },
      {
        "id": "9-5",
        "row": 9,
        "col": 5,
        "isBlack": false,
        "correctChar": "D",
        "userChar": "",
        "number": 49
      },
      {
        "id": "9-6",
        "row": 9,
        "col": 6,
        "isBlack": true,
        "correctChar": null,
        "userChar": ""
      },
      {
        "id": "9-7",
        "row": 9,
        "col": 7,
        "isBlack": true,
        "correctChar": null,
        "userChar": ""
      },
      {
        "id": "9-8",
        "row": 9,
        "col": 8,
        "isBlack": true,
        "correctChar": null,
        "userChar": ""
      },
      {
        "id": "9-9",
        "row": 9,
        "col": 9,
        "isBlack": false,
        "correctChar": "B",
        "userChar": "",
        "number": 50
      },
      {
        "id": "9-10",
        "row": 9,
        "col": 10,
        "isBlack": false,
        "correctChar": "E",
        "userChar": "",
        "number": 51
      },
      {
        "id": "9-11",
        "row": 9,
        "col": 11,
        "isBlack": false,
        "correctChar": "L",
        "userChar": "",
        "number": 52
      },
      {
        "id": "9-12",
        "row": 9,
        "col": 12,
        "isBlack": true,
        "correctChar": null,
        "userChar": ""
      },
      {
        "id": "9-13",
        "row": 9,
        "col": 13,
        "isBlack": true,
        "correctChar": null,
        "userChar": ""
      },
      {
        "id": "9-14",
        "row": 9,
        "col": 14,
        "isBlack": true,
        "correctChar": null,
        "userChar": ""
      }
    ],
    [
      {
        "id": "10-0",
        "row": 10,
        "col": 0,
        "isBlack": true,
        "correctChar": null,
        "userChar": ""
      },
      {
        "id": "10-1",
        "row": 10,
        "col": 1,
        "isBlack": false,
        "correctChar": "W",
        "userChar": "",
        "number": 53
      },
      {
        "id": "10-2",
        "row": 10,
        "col": 2,
        "isBlack": false,
        "correctChar": "A",
        "userChar": ""
      },
      {
        "id": "10-3",
        "row": 10,
        "col": 3,
        "isBlack": false,
        "correctChar": "R",
        "userChar": ""
      },
      {
        "id": "10-4",
        "row": 10,
        "col": 4,
        "isBlack": false,
        "correctChar": "M",
        "userChar": ""
      },
      {
        "id": "10-5",
        "row": 10,
        "col": 5,
        "isBlack": false,
        "correctChar": "U",
        "userChar": ""
      },
      {
        "id": "10-6",
        "row": 10,
        "col": 6,
        "isBlack": false,
        "correctChar": "P",
        "userChar": "",
        "number": 54
      },
      {
        "id": "10-7",
        "row": 10,
        "col": 7,
        "isBlack": true,
        "correctChar": null,
        "userChar": ""
      },
      {
        "id": "10-8",
        "row": 10,
        "col": 8,
        "isBlack": true,
        "correctChar": null,
        "userChar": ""
      },
      {
        "id": "10-9",
        "row": 10,
        "col": 9,
        "isBlack": true,
        "correctChar": null,
        "userChar": ""
      },
      {
        "id": "10-10",
        "row": 10,
        "col": 10,
        "isBlack": false,
        "correctChar": "S",
        "userChar": "",
        "number": 55
      },
      {
        "id": "10-11",
        "row": 10,
        "col": 11,
        "isBlack": false,
        "correctChar": "E",
        "userChar": ""
      },
      {
        "id": "10-12",
        "row": 10,
        "col": 12,
        "isBlack": false,
        "correctChar": "A",
        "userChar": "",
        "number": 56
      },
      {
        "id": "10-13",
        "row": 10,
        "col": 13,
        "isBlack": false,
        "correctChar": "N",
        "userChar": "",
        "number": 57
      },
      {
        "id": "10-14",
        "row": 10,
        "col": 14,
        "isBlack": true,
        "correctChar": null,
        "userChar": ""
      }
    ],
    [
      {
        "id": "11-0",
        "row": 11,
        "col": 0,
        "isBlack": false,
        "correctChar": "A",
        "userChar": "",
        "number": 58
      },
      {
        "id": "11-1",
        "row": 11,
        "col": 1,
        "isBlack": false,
        "correctChar": "I",
        "userChar": ""
      },
      {
        "id": "11-2",
        "row": 11,
        "col": 2,
        "isBlack": false,
        "correctChar": "C",
        "userChar": ""
      },
      {
        "id": "11-3",
        "row": 11,
        "col": 3,
        "isBlack": true,
        "correctChar": null,
        "userChar": ""
      },
      {
        "id": "11-4",
        "row": 11,
        "col": 4,
        "isBlack": true,
        "correctChar": null,
        "userChar": ""
      },
      {
        "id": "11-5",
        "row": 11,
        "col": 5,
        "isBlack": false,
        "correctChar": "B",
        "userChar": "",
        "number": 59
      },
      {
        "id": "11-6",
        "row": 11,
        "col": 6,
        "isBlack": false,
        "correctChar": "O",
        "userChar": ""
      },
      {
        "id": "11-7",
        "row": 11,
        "col": 7,
        "isBlack": false,
        "correctChar": "P",
        "userChar": "",
        "number": 60
      },
      {
        "id": "11-8",
        "row": 11,
        "col": 8,
        "isBlack": true,
        "correctChar": null,
        "userChar": ""
      },
      {
        "id": "11-9",
        "row": 11,
        "col": 9,
        "isBlack": false,
        "correctChar": "O",
        "userChar": "",
        "number": 61
      },
      {
        "id": "11-10",
        "row": 11,
        "col": 10,
        "isBlack": false,
        "correctChar": "S",
        "userChar": ""
      },
      {
        "id": "11-11",
        "row": 11,
        "col": 11,
        "isBlack": false,
        "correctChar": "E",
        "userChar": ""
      },
      {
        "id": "11-12",
        "row": 11,
        "col": 12,
        "isBlack": false,
        "correctChar": "R",
        "userChar": ""
      },
      {
        "id": "11-13",
        "row": 11,
        "col": 13,
        "isBlack": false,
        "correctChar": "E",
        "userChar": ""
      },
      {
        "id": "11-14",
        "row": 11,
        "col": 14,
        "isBlack": false,
        "correctChar": "I",
        "userChar": "",
        "number": 62
      }
    ],
    [
      {
        "id": "12-0",
        "row": 12,
        "col": 0,
        "isBlack": false,
        "correctChar": "S",
        "userChar": "",
        "number": 63
      },
      {
        "id": "12-1",
        "row": 12,
        "col": 1,
        "isBlack": false,
        "correctChar": "C",
        "userChar": ""
      },
      {
        "id": "12-2",
        "row": 12,
        "col": 2,
        "isBlack": false,
        "correctChar": "A",
        "userChar": ""
      },
      {
        "id": "12-3",
        "row": 12,
        "col": 3,
        "isBlack": false,
        "correctChar": "P",
        "userChar": "",
        "number": 64
      },
      {
        "id": "12-4",
        "row": 12,
        "col": 4,
        "isBlack": false,
        "correctChar": "P",
        "userChar": "",
        "number": 65
      },
      {
        "id": "12-5",
        "row": 12,
        "col": 5,
        "isBlack": false,
        "correctChar": "A",
        "userChar": ""
      },
      {
        "id": "12-6",
        "row": 12,
        "col": 6,
        "isBlack": false,
        "correctChar": "T",
        "userChar": ""
      },
      {
        "id": "12-7",
        "row": 12,
        "col": 7,
        "isBlack": false,
        "correctChar": "E",
        "userChar": ""
      },
      {
        "id": "12-8",
        "row": 12,
        "col": 8,
        "isBlack": false,
        "correctChar": "L",
        "userChar": "",
        "number": 66
      },
      {
        "id": "12-9",
        "row": 12,
        "col": 9,
        "isBlack": false,
        "correctChar": "L",
        "userChar": ""
      },
      {
        "id": "12-10",
        "row": 12,
        "col": 10,
        "isBlack": false,
        "correctChar": "E",
        "userChar": ""
      },
      {
        "id": "12-11",
        "row": 12,
        "col": 11,
        "isBlack": true,
        "correctChar": null,
        "userChar": ""
      },
      {
        "id": "12-12",
        "row": 12,
        "col": 12,
        "isBlack": false,
        "correctChar": "A",
        "userChar": "",
        "number": 67
      },
      {
        "id": "12-13",
        "row": 12,
        "col": 13,
        "isBlack": false,
        "correctChar": "L",
        "userChar": ""
      },
      {
        "id": "12-14",
        "row": 12,
        "col": 14,
        "isBlack": false,
        "correctChar": "P",
        "userChar": ""
      }
    ],
    [
      {
        "id": "13-0",
        "row": 13,
        "col": 0,
        "isBlack": false,
        "correctChar": "C",
        "userChar": "",
        "number": 68
      },
      {
        "id": "13-1",
        "row": 13,
        "col": 1,
        "isBlack": false,
        "correctChar": "H",
        "userChar": ""
      },
      {
        "id": "13-2",
        "row": 13,
        "col": 2,
        "isBlack": false,
        "correctChar": "R",
        "userChar": ""
      },
      {
        "id": "13-3",
        "row": 13,
        "col": 3,
        "isBlack": false,
        "correctChar": "I",
        "userChar": ""
      },
      {
        "id": "13-4",
        "row": 13,
        "col": 4,
        "isBlack": false,
        "correctChar": "S",
        "userChar": ""
      },
      {
        "id": "13-5",
        "row": 13,
        "col": 5,
        "isBlack": false,
        "correctChar": "T",
        "userChar": ""
      },
      {
        "id": "13-6",
        "row": 13,
        "col": 6,
        "isBlack": false,
        "correctChar": "O",
        "userChar": ""
      },
      {
        "id": "13-7",
        "row": 13,
        "col": 7,
        "isBlack": false,
        "correctChar": "P",
        "userChar": ""
      },
      {
        "id": "13-8",
        "row": 13,
        "col": 8,
        "isBlack": false,
        "correctChar": "H",
        "userChar": ""
      },
      {
        "id": "13-9",
        "row": 13,
        "col": 9,
        "isBlack": false,
        "correctChar": "E",
        "userChar": ""
      },
      {
        "id": "13-10",
        "row": 13,
        "col": 10,
        "isBlack": false,
        "correctChar": "R",
        "userChar": ""
      },
      {
        "id": "13-11",
        "row": 13,
        "col": 11,
        "isBlack": true,
        "correctChar": null,
        "userChar": ""
      },
      {
        "id": "13-12",
        "row": 13,
        "col": 12,
        "isBlack": false,
        "correctChar": "B",
        "userChar": "",
        "number": 69
      },
      {
        "id": "13-13",
        "row": 13,
        "col": 13,
        "isBlack": false,
        "correctChar": "L",
        "userChar": ""
      },
      {
        "id": "13-14",
        "row": 13,
        "col": 14,
        "isBlack": false,
        "correctChar": "A",
        "userChar": ""
      }
    ],
    [
      {
        "id": "14-0",
        "row": 14,
        "col": 0,
        "isBlack": true,
        "correctChar": null,
        "userChar": ""
      },
      {
        "id": "14-1",
        "row": 14,
        "col": 1,
        "isBlack": true,
        "correctChar": null,
        "userChar": ""
      },
      {
        "id": "14-2",
        "row": 14,
        "col": 2,
        "isBlack": false,
        "correctChar": "E",
        "userChar": "",
        "number": 70
      },
      {
        "id": "14-3",
        "row": 14,
        "col": 3,
        "isBlack": false,
        "correctChar": "I",
        "userChar": ""
      },
      {
        "id": "14-4",
        "row": 14,
        "col": 4,
        "isBlack": false,
        "correctChar": "S",
        "userChar": ""
      },
      {
        "id": "14-5",
        "row": 14,
        "col": 5,
        "isBlack": true,
        "correctChar": null,
        "userChar": ""
      },
      {
        "id": "14-6",
        "row": 14,
        "col": 6,
        "isBlack": false,
        "correctChar": "S",
        "userChar": "",
        "number": 71
      },
      {
        "id": "14-7",
        "row": 14,
        "col": 7,
        "isBlack": false,
        "correctChar": "E",
        "userChar": ""
      },
      {
        "id": "14-8",
        "row": 14,
        "col": 8,
        "isBlack": false,
        "correctChar": "R",
        "userChar": ""
      },
      {
        "id": "14-9",
        "row": 14,
        "col": 9,
        "isBlack": false,
        "correctChar": "G",
        "userChar": ""
      },
      {
        "id": "14-10",
        "row": 14,
        "col": 10,
        "isBlack": false,
        "correctChar": "E",
        "userChar": ""
      },
      {
        "id": "14-11",
        "row": 14,
        "col": 11,
        "isBlack": true,
        "correctChar": null,
        "userChar": ""
      },
      {
        "id": "14-12",
        "row": 14,
        "col": 12,
        "isBlack": false,
        "correctChar": "O",
        "userChar": "",
        "number": 72
      },
      {
        "id": "14-13",
        "row": 14,
        "col": 13,
        "isBlack": false,
        "correctChar": "E",
        "userChar": ""
      },
      {
        "id": "14-14",
        "row": 14,
        "col": 14,
        "isBlack": false,
        "correctChar": "D",
        "userChar": ""
      }
    ]
  ],
  "clues": [
    {
      "id": "a14c0d0b-9bfb-4309-b9fc-7faa585aa1fa",
      "number": 1,
      "direction": "across",
      "text": "Detto: Meglio tardi __ mai",
      "startRow": 0,
      "startCol": 0,
      "length": 3
    },
    {
      "id": "38e123ec-0e56-4db8-bf37-964bf818e797",
      "number": 1,
      "direction": "down",
      "text": "Liliana, celebre danzatrice",
      "startRow": 0,
      "startCol": 0,
      "length": 4
    },
    {
      "id": "5052975b-89df-44e9-83b3-4b32f5f52364",
      "number": 2,
      "direction": "down",
      "text": "Accoglie chi è fuori casa",
      "startRow": 0,
      "startCol": 1,
      "length": 5
    },
    {
      "id": "516b1931-1117-4fb6-933e-9afe3292bd0d",
      "number": 3,
      "direction": "down",
      "text": "Li sostengono i candidati",
      "startRow": 0,
      "startCol": 2,
      "length": 5
    },
    {
      "id": "582c5138-7018-406c-b544-329eaad22b8a",
      "number": 4,
      "direction": "across",
      "text": "Si abbarbica ai muri",
      "startRow": 0,
      "startCol": 4,
      "length": 5
    },
    {
      "id": "0737e399-1b95-4833-a724-ac3a754acca5",
      "number": 4,
      "direction": "down",
      "text": "Definizione per EVELYN",
      "startRow": 0,
      "startCol": 4,
      "length": 6
    },
    {
      "id": "76fc6a54-bd07-4d86-83f7-13c4814c6c87",
      "number": 5,
      "direction": "down",
      "text": "Fare le cose al meglio: come si __",
      "startRow": 0,
      "startCol": 5,
      "length": 4
    },
    {
      "id": "a0475af6-448b-494d-8c19-bd786e9e35f1",
      "number": 6,
      "direction": "down",
      "text": "Nome dell'attore Wallach",
      "startRow": 0,
      "startCol": 6,
      "length": 3
    },
    {
      "id": "d7939536-4b2c-4a7a-9e38-80b03ee4f86c",
      "number": 7,
      "direction": "down",
      "text": "Definizione per RODE",
      "startRow": 0,
      "startCol": 7,
      "length": 4
    },
    {
      "id": "c690a4b3-6d9f-4551-9ea0-e1ffe9fba24e",
      "number": 8,
      "direction": "down",
      "text": "Si usa per marinare",
      "startRow": 0,
      "startCol": 8,
      "length": 5
    },
    {
      "id": "ce417e76-f97e-4ebf-b77f-1a5c42e493f3",
      "number": 9,
      "direction": "across",
      "text": "Detto latino: Mors __, vita mea",
      "startRow": 0,
      "startCol": 10,
      "length": 3
    },
    {
      "id": "2b49e437-51cb-44e6-bdef-a0fc07fac7cd",
      "number": 9,
      "direction": "down",
      "text": "Definizione per TMZ",
      "startRow": 0,
      "startCol": 10,
      "length": 3
    },
    {
      "id": "f3bd91c8-2288-42c0-9ad2-97beef35ceaf",
      "number": 10,
      "direction": "down",
      "text": "Un richiamo popolare",
      "startRow": 0,
      "startCol": 11,
      "length": 3
    },
    {
      "id": "e56625a8-b1cb-46dd-be39-1aebdf1de45d",
      "number": 11,
      "direction": "down",
      "text": "Li risolve l'enigmista",
      "startRow": 0,
      "startCol": 12,
      "length": 9
    },
    {
      "id": "5d793e93-8764-4126-a853-379018d93aeb",
      "number": 12,
      "direction": "across",
      "text": "Out of Service (sigla)",
      "startRow": 1,
      "startCol": 0,
      "length": 3
    },
    {
      "id": "ec17779e-4baf-4071-ad2c-288214748c3d",
      "number": 13,
      "direction": "across",
      "text": "Molto in fretta",
      "startRow": 1,
      "startCol": 4,
      "length": 11
    },
    {
      "id": "06c2b506-9c52-4aae-bf3e-fd3bf5685e8f",
      "number": 14,
      "direction": "down",
      "text": "Località del Vicentino sull'Altipiano dei Sette Comuni",
      "startRow": 1,
      "startCol": 9,
      "length": 5
    },
    {
      "id": "e588dffb-7df5-4561-991a-de08b1557802",
      "number": 15,
      "direction": "down",
      "text": "Definizione per TREASURE",
      "startRow": 1,
      "startCol": 13,
      "length": 8
    },
    {
      "id": "6473eb5d-e9c5-465b-9ea8-ba810ac8a5bc",
      "number": 16,
      "direction": "down",
      "text": "European Environment Bureau",
      "startRow": 1,
      "startCol": 14,
      "length": 3
    },
    {
      "id": "3a720bfe-37c8-42e2-b7cc-95e6e7c1edd0",
      "number": 17,
      "direction": "across",
      "text": "Abbreviami questa",
      "startRow": 2,
      "startCol": 0,
      "length": 3
    },
    {
      "id": "c47c1ee3-5f8b-4903-9e0d-3283f1968698",
      "number": 18,
      "direction": "across",
      "text": "Mettere in risalto",
      "startRow": 2,
      "startCol": 4,
      "length": 11
    },
    {
      "id": "9ed86766-8faf-45eb-aa32-c28c8267bc0d",
      "number": 19,
      "direction": "across",
      "text": "Relativo all'inverno in poesia",
      "startRow": 3,
      "startCol": 0,
      "length": 6
    },
    {
      "id": "8c10407b-32c7-4854-9f82-06ad3d947940",
      "number": 20,
      "direction": "down",
      "text": "Tutti in inglese",
      "startRow": 3,
      "startCol": 3,
      "length": 3
    },
    {
      "id": "966c3b9b-3e56-4e99-9c29-3aa2e9d0c5d9",
      "number": 21,
      "direction": "across",
      "text": "Vivo, sfocia presso Porto San Giorgio",
      "startRow": 3,
      "startCol": 7,
      "length": 3
    },
    {
      "id": "4ac82990-2ad2-4ada-89b4-c0c363a7147a",
      "number": 22,
      "direction": "across",
      "text": "Il capolavoro di Douglas Hofstadter, dedicato a un logico, a un artista e a un musicista (sigla)",
      "startRow": 3,
      "startCol": 12,
      "length": 3
    },
    {
      "id": "9fdb66f9-6701-460a-9385-89c8f3395495",
      "number": 23,
      "direction": "across",
      "text": "Allen cantante",
      "startRow": 4,
      "startCol": 1,
      "length": 4
    },
    {
      "id": "f5b1a808-0aa8-47d7-8583-8d3bdc2893d3",
      "number": 24,
      "direction": "across",
      "text": "Lo stesso che sempre",
      "startRow": 4,
      "startCol": 8,
      "length": 6
    },
    {
      "id": "cb2563c8-f9b9-47a5-8f62-4c2cbcb9dbb7",
      "number": 25,
      "direction": "down",
      "text": "Ne è uscito Schifani (sigla)",
      "startRow": 4,
      "startCol": 10,
      "length": 3
    },
    {
      "id": "4284c6f9-1b34-4a30-bd63-23c65b24317a",
      "number": 26,
      "direction": "down",
      "text": "Il vero nome di Dario II di Persia",
      "startRow": 4,
      "startCol": 11,
      "length": 3
    },
    {
      "id": "1395d606-3112-4048-a930-883031da3874",
      "number": 27,
      "direction": "across",
      "text": "Lega Nazionale Naturisti",
      "startRow": 5,
      "startCol": 3,
      "length": 3
    },
    {
      "id": "3294bca9-f204-4f80-ba34-fb012a6b174a",
      "number": 28,
      "direction": "down",
      "text": "Io e voi",
      "startRow": 5,
      "startCol": 5,
      "length": 3
    },
    {
      "id": "3ba21bc1-668f-485a-8e05-043b7ce52ece",
      "number": 29,
      "direction": "across",
      "text": "Poetico tramonto",
      "startRow": 5,
      "startCol": 9,
      "length": 6
    },
    {
      "id": "5aed9f1c-be19-402f-a238-968057b7dba0",
      "number": 30,
      "direction": "down",
      "text": "Se ne fanno bottoni",
      "startRow": 5,
      "startCol": 14,
      "length": 4
    },
    {
      "id": "aec4b5e9-8bad-404a-81c4-d8e574799c0d",
      "number": 31,
      "direction": "across",
      "text": "Un fiume del Piceno",
      "startRow": 6,
      "startCol": 0,
      "length": 3
    },
    {
      "id": "de673297-62ca-4a89-b50e-bef6c335cf79",
      "number": 31,
      "direction": "down",
      "text": "Un vezzeggiativo per Abraham",
      "startRow": 6,
      "startCol": 0,
      "length": 4
    },
    {
      "id": "f94653cc-25a3-4a04-ace8-a8ca76cbeb40",
      "number": 32,
      "direction": "down",
      "text": "È simile al tramezzino",
      "startRow": 6,
      "startCol": 1,
      "length": 8
    },
    {
      "id": "312ab70b-088e-4369-a608-e55dfb6dbc47",
      "number": 33,
      "direction": "down",
      "text": "Una bestia nera per Trump",
      "startRow": 6,
      "startCol": 2,
      "length": 9
    },
    {
      "id": "49ff6129-58aa-4c6d-a3f9-cbc0742bf2e2",
      "number": 34,
      "direction": "across",
      "text": "Tra ieri e domani",
      "startRow": 6,
      "startCol": 5,
      "length": 4
    },
    {
      "id": "2e5e6346-2053-4e1b-876f-202ddf724848",
      "number": 35,
      "direction": "down",
      "text": "L'articolo per... altri",
      "startRow": 6,
      "startCol": 6,
      "length": 3
    },
    {
      "id": "a286ac26-7f78-4d77-bf65-3b3d042644f9",
      "number": 36,
      "direction": "down",
      "text": "Arriva ai fornelli dentro un tubo",
      "startRow": 6,
      "startCol": 7,
      "length": 3
    },
    {
      "id": "cbb556b9-cb8e-4254-b465-1a32697c155d",
      "number": 37,
      "direction": "down",
      "text": "Segue il nome di certe società americane (abbr.)",
      "startRow": 6,
      "startCol": 8,
      "length": 3
    },
    {
      "id": "7254b189-dec1-437a-afe3-a070860ba546",
      "number": 38,
      "direction": "across",
      "text": "Quella aurea era la residenza di Nerone",
      "startRow": 6,
      "startCol": 10,
      "length": 5
    },
    {
      "id": "f5950f25-b855-4ab2-8f1f-1eeb92828623",
      "number": 39,
      "direction": "across",
      "text": "Bed and Breakfast",
      "startRow": 7,
      "startCol": 0,
      "length": 3
    },
    {
      "id": "459358c5-a0fa-4f9a-939c-0160fa073882",
      "number": 40,
      "direction": "across",
      "text": "Vi giovava Rivera",
      "startRow": 7,
      "startCol": 5,
      "length": 5
    },
    {
      "id": "1a5472de-4dcc-42ec-8317-ccf9710a37e1",
      "number": 41,
      "direction": "down",
      "text": "Il Roy di un romanzo di Scott",
      "startRow": 7,
      "startCol": 9,
      "length": 3
    },
    {
      "id": "f06a60e6-d973-4052-b394-c765b41e0655",
      "number": 42,
      "direction": "across",
      "text": "Abbreviazione di \"mistress\"",
      "startRow": 7,
      "startCol": 12,
      "length": 3
    },
    {
      "id": "948749d9-c90f-447c-a5a7-c285ff6dcc16",
      "number": 43,
      "direction": "across",
      "text": "Vigilio storico grecista",
      "startRow": 8,
      "startCol": 0,
      "length": 5
    },
    {
      "id": "6eef6875-d850-4f47-9e39-58442c32e0eb",
      "number": 44,
      "direction": "down",
      "text": "Carlo Guido, storico italiano",
      "startRow": 8,
      "startCol": 3,
      "length": 3
    },
    {
      "id": "48aa1f21-8de2-411f-85a4-4584a7d0ad19",
      "number": 45,
      "direction": "down",
      "text": "La sigla dell'associazione nazionale magistrati",
      "startRow": 8,
      "startCol": 4,
      "length": 3
    },
    {
      "id": "71ac9f27-3388-46f8-b524-9dee56adf7c3",
      "number": 46,
      "direction": "across",
      "text": "Sigla d'un Istituto che studia la congiuntura",
      "startRow": 8,
      "startCol": 6,
      "length": 4
    },
    {
      "id": "9cb51d50-84e8-4735-9c0b-1dd299fc93cd",
      "number": 47,
      "direction": "across",
      "text": "Le vocali nel cielo",
      "startRow": 8,
      "startCol": 12,
      "length": 3
    },
    {
      "id": "e99404d6-53a0-490d-82e2-e927707388b9",
      "number": 48,
      "direction": "across",
      "text": "Il Dantés che diventa Conte di Montecristo",
      "startRow": 9,
      "startCol": 0,
      "length": 6
    },
    {
      "id": "0af28edd-08bb-4393-8e52-6c4d423718bc",
      "number": 49,
      "direction": "down",
      "text": "Ex soldati coloniali",
      "startRow": 9,
      "startCol": 5,
      "length": 5
    },
    {
      "id": "12b55473-25cb-41b7-8bf9-cb30db2efb83",
      "number": 50,
      "direction": "across",
      "text": "Così si dice del nostro Paese",
      "startRow": 9,
      "startCol": 9,
      "length": 3
    },
    {
      "id": "2a926970-0ade-4964-8c96-3f7b65a81d27",
      "number": 51,
      "direction": "down",
      "text": "Si oppone all' avere",
      "startRow": 9,
      "startCol": 10,
      "length": 6
    },
    {
      "id": "83a3e318-5d5f-446f-aab5-6219c12eccdc",
      "number": 52,
      "direction": "down",
      "text": "Guidò l'esercito sudista",
      "startRow": 9,
      "startCol": 11,
      "length": 3
    },
    {
      "id": "d5df2d57-c741-4a9f-9358-6e541dc0bd86",
      "number": 53,
      "direction": "across",
      "text": "Il riscaldamento meccanico",
      "startRow": 10,
      "startCol": 1,
      "length": 6
    },
    {
      "id": "ebbe1949-7279-4a53-bf54-544daa54e39d",
      "number": 54,
      "direction": "down",
      "text": "Un genere di mammiferi procionidi",
      "startRow": 10,
      "startCol": 6,
      "length": 5
    },
    {
      "id": "65349091-930e-4f7a-993c-d3e440abcd50",
      "number": 55,
      "direction": "across",
      "text": "Il Penn attore",
      "startRow": 10,
      "startCol": 10,
      "length": 4
    },
    {
      "id": "9c96091c-4e32-4245-b632-29e3cdf735fe",
      "number": 56,
      "direction": "down",
      "text": "Lo parlano i Beduini",
      "startRow": 10,
      "startCol": 12,
      "length": 5
    },
    {
      "id": "b023be44-190f-40e3-8950-99dc0f5436eb",
      "number": 57,
      "direction": "down",
      "text": "Dentro le",
      "startRow": 10,
      "startCol": 13,
      "length": 5
    },
    {
      "id": "c4762d3f-4b63-48a0-b673-952ce5ef4996",
      "number": 58,
      "direction": "across",
      "text": "Associa calciatori (sigla)",
      "startRow": 11,
      "startCol": 0,
      "length": 3
    },
    {
      "id": "ad963b6e-2554-4d08-899e-e857a0c59f0f",
      "number": 58,
      "direction": "down",
      "text": "American Society of Cinematographers",
      "startRow": 11,
      "startCol": 0,
      "length": 3
    },
    {
      "id": "16208fb5-d3d1-43e0-a522-c3147f33c379",
      "number": 59,
      "direction": "across",
      "text": "Uno stile del jazz",
      "startRow": 11,
      "startCol": 5,
      "length": 3
    },
    {
      "id": "d2927e67-9069-4565-ae4e-558fc05fa10c",
      "number": 60,
      "direction": "down",
      "text": "Non manca nella dispensa",
      "startRow": 11,
      "startCol": 7,
      "length": 4
    },
    {
      "id": "22734fd5-13c2-499a-b9b8-0968f6cfbc97",
      "number": 61,
      "direction": "across",
      "text": "Definizione per OSEREI",
      "startRow": 11,
      "startCol": 9,
      "length": 6
    },
    {
      "id": "5ea58a28-d631-4714-9fe2-694d51d021a7",
      "number": 61,
      "direction": "down",
      "text": "Il Cassini celebre sarto",
      "startRow": 11,
      "startCol": 9,
      "length": 4
    },
    {
      "id": "dca13142-a8e6-4bdc-9912-ef887947d3c1",
      "number": 62,
      "direction": "down",
      "text": "Una tavoletta tecnologica.",
      "startRow": 11,
      "startCol": 14,
      "length": 4
    },
    {
      "id": "e0e1eb8a-7963-4839-a4e2-50e1d064a39b",
      "number": 63,
      "direction": "across",
      "text": "Definizione per SCAPPATELLE",
      "startRow": 12,
      "startCol": 0,
      "length": 11
    },
    {
      "id": "6a26e779-e48b-464e-a363-e28a74c720d5",
      "number": 64,
      "direction": "down",
      "text": "Così restano certi desideri",
      "startRow": 12,
      "startCol": 3,
      "length": 3
    },
    {
      "id": "c95cd45e-2db3-42f0-a764-fe4cf7ba01d0",
      "number": 65,
      "direction": "down",
      "text": "Sibilo che richiama l' attenzione",
      "startRow": 12,
      "startCol": 4,
      "length": 3
    },
    {
      "id": "6e0b2b9f-3ba7-4ef3-8a4c-c08b86c2d2f3",
      "number": 66,
      "direction": "down",
      "text": "Sigla di un aeroporto di Londra",
      "startRow": 12,
      "startCol": 8,
      "length": 3
    },
    {
      "id": "b38bca55-66d5-4260-9d5d-318fd7fb7b75",
      "number": 67,
      "direction": "across",
      "text": "Australian Labor Party",
      "startRow": 12,
      "startCol": 12,
      "length": 3
    },
    {
      "id": "6389d68c-9def-43d2-aadf-f9c3abccef2d",
      "number": 68,
      "direction": "across",
      "text": "Definizione per CHRISTOPHER",
      "startRow": 13,
      "startCol": 0,
      "length": 11
    },
    {
      "id": "4fbf2445-fd41-4d6c-ae61-f03955fd5c33",
      "number": 69,
      "direction": "across",
      "text": "Ripetuto è un chiacchiericcio",
      "startRow": 13,
      "startCol": 12,
      "length": 3
    },
    {
      "id": "ac306667-0683-4fc4-85e1-ecb73ce2babd",
      "number": 70,
      "direction": "across",
      "text": "Ghiaccio in Germania",
      "startRow": 14,
      "startCol": 2,
      "length": 3
    },
    {
      "id": "55e85548-938b-47f1-8b6e-8448ad802eda",
      "number": 71,
      "direction": "across",
      "text": "Un Reggiani del cinema",
      "startRow": 14,
      "startCol": 6,
      "length": 5
    },
    {
      "id": "341aae83-a678-453c-a36c-35b29b1f6af8",
      "number": 72,
      "direction": "across",
      "text": "Oxford English Dictionnary (sigla)",
      "startRow": 14,
      "startCol": 12,
      "length": 3
    }
  ]
}